{
    "source": "https://vkuso.ru/recipe/106460-bujabes-kak-v-kino/",
    "category": "Супы",
    "category_slug": "supy",
    "title": "Буйабес как в кино",
    "description": "Этот рецепт присутствует в популярном сериале «Кухня». Настоящий хит повара Баринова",
    "note": "Готовый суп также можно украсить листочками базилика или петрушки.",
    "cuisine": "Французская кухня",
    "cuisine_slug": "francuzskaya-kuhnya",
    "poster": "https://st.vkuso.ru/data/cache/thumb/f2/2de72e6af7425f2_660x440.jpg",
    "difficulty": "Средняя",
    "cooktime": "2 часа",
    "preparetime": null,
    "video": null,
    "vegan": false,
    "ingredients": [
        {
            "name": "Ингредиенты на 6 порции",
            "list": [
                {
                    "name": "сибас",
                    "slug": "sibas",
                    "notes": null,
                    "value": "600",
                    "type": "г",
                    "amount": null
                },
                {
                    "name": "лосось",
                    "slug": "losos",
                    "notes": null,
                    "value": "500",
                    "type": "г",
                    "amount": null
                },
                {
                    "name": "субпродукты",
                    "slug": "subprodukty",
                    "notes": " (кости)",
                    "value": "500",
                    "type": "г",
                    "amount": null
                },
                {
                    "name": "креветки",
                    "slug": "krevetki",
                    "notes": null,
                    "value": "300",
                    "type": "г",
                    "amount": null
                },
                {
                    "name": "помидоры в собственном соку",
                    "slug": "pomidory-v-sobstvennom-soku",
                    "notes": null,
                    "value": "½",
                    "type": "банки",
                    "amount": null
                },
                {
                    "name": "масло оливковое",
                    "slug": "maslo-olivkovoe",
                    "notes": null,
                    "value": "100",
                    "type": "мл",
                    "amount": null
                },
                {
                    "name": "лук-шалот",
                    "slug": "luk-shalot",
                    "notes": null,
                    "value": "2",
                    "type": "шт.",
                    "amount": null
                },
                {
                    "name": "кальмары",
                    "slug": "kalmary",
                    "notes": null,
                    "value": "1",
                    "type": "шт.",
                    "amount": null
                },
                {
                    "name": "лук репчатый",
                    "slug": "luk-repchatiy",
                    "notes": null,
                    "value": "1",
                    "type": "шт.",
                    "amount": null
                },
                {
                    "name": "морковь",
                    "slug": "morkov",
                    "notes": null,
                    "value": "1",
                    "type": "шт.",
                    "amount": null
                },
                {
                    "name": "сельдерей",
                    "slug": "selderey",
                    "notes": null,
                    "value": "3",
                    "type": "стебля",
                    "amount": null
                },
                {
                    "name": "чеснок",
                    "slug": "chesnok",
                    "notes": null,
                    "value": "3",
                    "type": "зубчика",
                    "amount": null
                },
                {
                    "name": "багет",
                    "slug": "baget",
                    "notes": null,
                    "value": "½",
                    "type": "шт.",
                    "amount": null
                },
                {
                    "name": "черемша",
                    "slug": "cheremsha",
                    "notes": null,
                    "value": "½",
                    "type": "пучка",
                    "amount": null
                },
                {
                    "name": "зелень петрушки",
                    "slug": "zelen-petrushki",
                    "notes": null,
                    "value": "½",
                    "type": "пучка",
                    "amount": null
                },
                {
                    "name": "яичный желток",
                    "slug": "yaichniy-jeltok",
                    "notes": null,
                    "value": "1",
                    "type": "шт.",
                    "amount": null
                },
                {
                    "name": "паприка",
                    "slug": "paprika",
                    "notes": null,
                    "value": "2",
                    "type": "щепотки",
                    "amount": null
                },
                {
                    "name": "шафран",
                    "slug": "shafran",
                    "notes": null,
                    "value": "1",
                    "type": "щепотка",
                    "amount": null
                },
                {
                    "name": "перец кайенский молотый",
                    "slug": "perec-kayenskiy-molotiy",
                    "notes": null,
                    "value": "1",
                    "type": "щепотка",
                    "amount": null
                },
                {
                    "name": "перец черный горошком",
                    "slug": "perec-cherniy-goroshkom",
                    "notes": null,
                    "value": "6",
                    "type": "шт.",
                    "amount": null
                }
            ]
        }
    ],
    "instruction": [
        {
            "text": "Лосось и сибас очистить, удалить кости.",
            "image": null
        },
        {
            "text": "Очистить кальмара и креветки.",
            "image": null
        },
        {
            "text": "Выложить в кастрюлю головы без жабр и глаз, кости, плавники, хвосты, головы и панцири креветок.",
            "image": null
        },
        {
            "text": "Влить два литра кипящей воды, довести до кипения.",
            "image": null
        },
        {
            "text": "В кипящий бульон выложить очищенную луковицу, морковь, стебли сельдерея, петрушку и черемшу, перец-горошек. Варить все вместе в течение сорока минут, огонь – средний.",
            "image": null
        },
        {
            "text": "Нарезать кубиками лук-шалот, оставшийся сельдерей, чеснок.",
            "image": null
        },
        {
            "text": "Прогреть оливковое масло в кастрюле с толстым дном. Выложить овощи, прогревать до мягкости.",
            "image": null
        },
        {
            "text": "Влить томаты в собственном соку, перемешать, тушить две минуты.",
            "image": null
        },
        {
            "text": "Добавить процеженный рыбный бульон. Варить все вместе на тихом огне пятнадцать минут.",
            "image": null
        },
        {
            "text": "Нарезать кусками рыбное филе, кальмара – полукольцами.",
            "image": null
        },
        {
            "text": "Выложить порциями в основной бульон с овощами.",
            "image": null
        },
        {
            "text": "Первый этап – добавление лосося, белая рыба – через две минуты, еще через три минуты – кальмары и креветки.",
            "image": null
        },
        {
            "text": "Варить две минуты, огонь погасить.",
            "image": null
        },
        {
            "text": "Поставить суп в тепло на десять или пятнадцать минут.",
            "image": null
        },
        {
            "text": "Приготовить соус: перемешать кайенский перец с сырым куриным желтком, шафраном, паприкой. Посолить по вкусу.",
            "image": null
        },
        {
            "text": "Взбить массу при помощи кулинарного венчика, ввести порциями оливковое масло. Готовая консистенция должна напоминать майонез.",
            "image": null
        },
        {
            "text": "Нарезать белый багет, побрызгать оливковым маслом, посушить в духовом шкафу при температуре 200 градусов.",
            "image": null
        },
        {
            "text": "Намазать соусом, украсить базиликом.",
            "image": null
        }
    ],
    "tags": [
        {
            "name": "Буйабес",
            "slug": "buyabes"
        },
        {
            "name": "Рыбный суп",
            "slug": "rybniy-sup"
        },
        {
            "name": "Суп без картошки",
            "slug": "sup-bez-kartoshki"
        },
        {
            "name": "Суп из лосося",
            "slug": "sup-iz-lososya"
        },
        {
            "name": "Суп из морепродуктов",
            "slug": "sup-iz-moreproduktov"
        },
        {
            "name": "Суп из сельдерея",
            "slug": "sup-iz-seldereya"
        },
        {
            "name": "Суп с кальмарами",
            "slug": "sup-s-kalmarami"
        },
        {
            "name": "Суп с креветками",
            "slug": "sup-s-krevetkami"
        }
    ]
}